relay/__init__.py
relay/client.py
relay/dashboard.py
relay/models.py
relay/persistence.py
relay/dashboard/static/dashboard.css
relay/dashboard/static/dashboard.js
relay/dashboard/static/index.html
relay/providers/__init__.py
relay/providers/anthropic.py
relay/providers/base.py
relay/providers/openai.py
relay/providers/together.py
relay_llm-0.2.0.dist-info/licenses/LICENSE
relay_llm-0.2.0.dist-info/METADATA
relay_llm-0.2.0.dist-info/WHEEL
relay_llm-0.2.0.dist-info/entry_points.txt
relay_llm-0.2.0.dist-info/top_level.txt
relay_llm-0.2.0.dist-info/RECORD
