Metadata-Version: 2.4
Name: relay-llm
Version: 0.2.0
Summary: A Python package for batch API calls to commercial LLM APIs
Home-page: https://github.com/neelguha/relay
Author: Neel Guha
Author-email: Neel Guha <neelguha@gmail.com>
License: MIT
Project-URL: Homepage, https://github.com/neelguha/relay
Project-URL: Documentation, https://github.com/neelguha/relay#readme
Project-URL: Repository, https://github.com/neelguha/relay
Project-URL: Issues, https://github.com/neelguha/relay/issues
Keywords: llm,batch,api,openai,anthropic,together,ai
Classifier: Development Status :: 3 - Alpha
Classifier: Intended Audience :: Developers
Classifier: License :: OSI Approved :: MIT License
Classifier: Programming Language :: Python :: 3
Classifier: Programming Language :: Python :: 3.8
Classifier: Programming Language :: Python :: 3.9
Classifier: Programming Language :: Python :: 3.10
Classifier: Programming Language :: Python :: 3.11
Classifier: Topic :: Software Development :: Libraries :: Python Modules
Classifier: Topic :: Scientific/Engineering :: Artificial Intelligence
Requires-Python: >=3.8
License-File: LICENSE
Requires-Dist: openai>=1.0.0
Provides-Extra: dev
Requires-Dist: pytest>=7.0.0; extra == "dev"
Requires-Dist: pytest-cov>=4.0.0; extra == "dev"
Requires-Dist: black>=23.0.0; extra == "dev"
Requires-Dist: flake8>=6.0.0; extra == "dev"
Requires-Dist: mypy>=1.0.0; extra == "dev"
Provides-Extra: dashboard
Requires-Dist: flask>=3.0.0; extra == "dashboard"
Dynamic: author
Dynamic: home-page
Dynamic: license-file
Dynamic: requires-python
